broker_client/__init__.py
broker_client/access_control.py
broker_client/consumer.py
broker_client/economy.py
broker_client/files.py
broker_client/reputation.py
broker_client/service.py
broker_client-1.0.0.dist-info/METADATA
broker_client-1.0.0.dist-info/WHEEL
broker_client-1.0.0.dist-info/top_level.txt
broker_client-1.0.0.dist-info/RECORD
