Metadata-Version: 2.1
Name: broker-client
Version: 1.0.0
Summary: A client for the Swarm Broker written in Python
Home-page: UNKNOWN
Author: Geovane Fedrecheski
Author-email: UNKNOWN
License: UNKNOWN
Platform: UNKNOWN
